vtkhdf/__init__.py
vtkhdf/image.py
vtk_hdf-0.2.0.dist-info/LICENSE
vtk_hdf-0.2.0.dist-info/METADATA
vtk_hdf-0.2.0.dist-info/WHEEL
vtk_hdf-0.2.0.dist-info/top_level.txt
vtk_hdf-0.2.0.dist-info/RECORD
