Metadata-Version: 2.2
Name: vtk-hdf
Version: 0.2.0
Summary: Python wrapper library for the new VTK HDF format.
Author-email: Jared Magnusson <jmag722@gmail.com>
License:                                  Apache License
Project-URL: Homepage, https://github.com/jmag722/vtk-hdf
Project-URL: Bug Reports, https://github.com/jmag722/vtk-hdf/issues
Keywords: vtk-hdf,python,pyvista,vtk,hdf5,h5py,visualization,wrapper,vtkhdf
Classifier: Programming Language :: Python :: 3 :: Only
Classifier: Operating System :: OS Independent
Requires-Python: >=3.9
License-File: LICENSE
Requires-Dist: h5py
Requires-Dist: numpy
Requires-Dist: pyvista>=0.40.0
Requires-Dist: vtk>=9.1.0
